[
   
    {
        "id": "1",
        "titulo": "Medialunas",
        "descripcion": "Producto congelado, con precocción",
        "imagen": "../img/Medialunasx3.jpg",
        "categoria": "Desayunos",
        "precio": 2500,
        "stock": 10
    },
    {
        "id": "2",
        "titulo": "Donout",
        "descripcion": "Producto congelado, con precocción",
        "imagen": "../img/DONOUT.jpg",
        "categoria": "Desayunos",
        "precio": 2900,
        "stock": 10
    },
    {
        "id": "3",
        "titulo": "Alfajor de Choco",
        "descripcion": "Producto congelado, con precocción",
        "imagen": "../img/ALf_Choco.jpg",
        "categoria": "Desayunos",
        "precio": 2500,
        "stock": 10
    },
    {
        "id": "4",
        "titulo": "Alfajor de Maicena",
        "descripcion": "Producto congelado, con precocción",
        "imagen": "../img/ALF_Maicena.jpg",
        "categoria": "Desayunos",
        "precio": 2500,
        "stock": 10
    },
    {
        "id": "5",
        "titulo": "Tostadas",
        "descripcion": "Producto congelado, con precocción",
        "imagen": "../img/tostadas.jpg",
        "categoria": "Desayunos",
        "precio": 3500,
        "stock": 10
    },
    {
        "id": "6",
        "titulo": "Muffin",
        "descripcion": "Producto congelado, con precocción",
        "imagen": "../img/MuffinDDL-300x300.jpg",
        "categoria": "Desayunos",
        "precio": 1500,
        "stock": 10
    },
    {
        "id": "7",
        "titulo": "Pan de Choco",
        "descripcion": "Producto congelado, con precocción",
        "imagen": "../img/PandeChoco-1-300x300.jpg",
        "categoria": "Desayunos",
        "precio": 2500,
        "stock": 10
    },
    
    {
        "id": "8",
        "titulo": "Frola",
        "descripcion": "Producto congelado, con precocción",
        "imagen": "../img/PASTAFROLA-1-300x300.jpg",
        "categoria": "Meriendas",
        "precio": 2000,
        "stock": 10
    },
    {
        "id": "9",
        "titulo": "Brownie",
        "descripcion": "Producto congelado, con precocción",
        "imagen": "../img/BROWNIE-1-300x300.jpg",
        "categoria": "Meriendas",
        "precio": 2000,
        "stock": 10
    },
    {
        "id": "10",
        "descripcion": "Producto congelado, con precocción",
        "titulo": "Bagel Tres Quesos",
        "imagen": "../img/BAGEL_JyQ.jpg",
        "categoria": "Meriendas",
        "precio": 2500,
        "stock": 10
    },
    {
        "id": "11",
        "titulo": "Budin Frutos Secos",
        "descripcion": "Producto congelado, con precocción",
        "imagen": "../img/BUDIN_Frutossecos-1-300x300.jpg",
        "categoria": "Meriendas",
        "precio": 2500,
        "stock": 10
    },
    {
        "id": "12",
        "titulo": "Croque",
        "descripcion": "Producto congelado, con precocción",
        "imagen": "../img/CroqueMonsieur-300x300.jpg",
        "categoria": "Meriendas",
        "precio": 2500,
        "stock": 10
    },
    {
        "id": "13",
        "titulo": "Budin Banana y DDL",
        "descripcion": "Producto congelado, con precocción",
        "imagen": "../img/BUDIN_BananaDDL-300x300.jpg",
        "categoria": "Meriendas",
        "precio": 2500,
        "stock": 10
    },
   
    {
        "id": "14",
        "titulo": "Hamburguesa",
        "descripcion": "Producto congelado, con precocción",
        "imagen": "../img/Almuerzo.jpg",
        "categoria": "Almuerzos",
        "precio": 5500,
        "stock": 10
    },
    {
        "id": "15",
        "titulo": "Ensalada Cesar",
        "descripcion": "Producto congelado, con precocción",
        "imagen": "../img/Ensalada-Cesar-cortada-600x443-1-300x300.jpg",
        "categoria": "Almuerzos",
        "precio": 4500,
        "stock": 10
    },
    {
        "id": "16",
        "titulo": "Ensalada Mix vegetales",
        "descripcion": "Producto congelado, con precocción",
        "imagen": "../img/EnsaladaMixde-Veg.jpg",
        "categoria": "Almuerzos",
        "precio": 4500,
        "stock": 10
    },
    {
        "id": "17",
        "titulo": "Empanadas",
        "descripcion": "Producto congelado, con precocción",
        "imagen": "../img/EMPANADAS-1-300x300.jpg",
        "categoria": "Almuerzos",
        "precio": 2500,
        "stock": 10
    },
    {
        "id": "18",
        "titulo": "Panini J y Q",
        "descripcion": "Producto congelado, con precocción",
        "imagen": "../img/PAniniJQTH.jpg",
        "categoria": "Almuerzos",
        "precio": 3500,
        "stock": 10
    },
    {
        "id": "19",
        "titulo": "Pebete",
        "descripcion": "Producto congelado, con precocción",
        "imagen": "../img/pebete.jpg",
        "categoria": "Almuerzos",
        "precio": 2500,
        "stock": 10
    },
    {
        "id": "20",
        "titulo": "Sandwich",
        "descripcion": "Producto congelado, con precocción",
        "imagen": "../img/TrianguloPollo.jpg",
        "categoria": "Almuerzos",
        "precio": 3000,
        "stock": 10
    },
    {
        "id": "21",
        "titulo": "Bagel",
        "descripcion": "Producto congelado, con precocción",
        "imagen": "../img/BAGEL_JyQ.jpg",
        "categoria": "Almuerzos",
        "precio": 3000,
        "stock": 10
    }
]

